gitlab_pages_upload/__init__.py
gitlab_pages_upload/__main__.py
gitlab_pages_upload/argbuilder.py
gitlab_pages_upload/cli.py
gitlab_pages_upload/config.py
gitlab_pages_upload/constants.py
gitlab_pages_upload/exec.py
gitlab_pages_upload/git_ops.py
gitlab_pages_upload/gitlab_api.py
gitlab_pages_upload/upload.py
gitlab_pages_upload/version.py
gitlab_pages_upload-0.3.0.dist-info/METADATA
gitlab_pages_upload-0.3.0.dist-info/WHEEL
gitlab_pages_upload-0.3.0.dist-info/entry_points.txt
gitlab_pages_upload-0.3.0.dist-info/licenses/LICENSE
gitlab_pages_upload-0.3.0.dist-info/RECORD
