Metadata-Version: 2.4
Name: gitlab-pages-upload
Version: 0.3.0
Summary: Publish versioned static HTML documentation to GitLab Pages
Project-URL: Repository, https://gitlab.com/cyberassessmentlabs/public/tools/gitlab-pages-upload
Project-URL: Documentation, https://cyberassessmentlabs.gitlab.io/public/docs/gitlab-pages-upload/latest/
Author: Cyber Assessment Labs
License-Expression: MIT
License-File: LICENSE
Keywords: docs,documentation,gitlab,gitlab-pages,static-site,upload
Classifier: Development Status :: 4 - Beta
Classifier: Environment :: Console
Classifier: Intended Audience :: Developers
Classifier: License :: OSI Approved :: MIT License
Classifier: Operating System :: OS Independent
Classifier: Programming Language :: Python :: 3
Classifier: Programming Language :: Python :: 3.14
Classifier: Topic :: Documentation
Classifier: Topic :: Software Development :: Documentation
Classifier: Typing :: Typed
Requires-Python: >=3.14
